README.md
setup.py
xl_tool/__init__.py
xl_tool/xl_concurrence.py
xl_tool/xl_general.py
xl_tool/xl_io.py
xl_tool.egg-info/PKG-INFO
xl_tool.egg-info/SOURCES.txt
xl_tool.egg-info/dependency_links.txt
xl_tool.egg-info/requires.txt
xl_tool.egg-info/top_level.txt
xl_tool/data/__init__.py
xl_tool/data/image/__init__.py
xl_tool/data/image/analysis.py
xl_tool/data/image/annonation.py
xl_tool/data/image/blending.py
xl_tool/data/image/config.py
xl_tool/data/image/general.py
xl_tool/data/image/batch/__init__.py
xl_tool/data/image/batch/augmentation.py