Metadata-Version: 2.1
Name: xl-tool
Version: 0.1.1
Summary: my tool function
Home-page: UNKNOWN
Author: Xiaolin
Author-email: 119xiaolin@163.com
License: UNKNOWN
Platform: UNKNOWN
Classifier: Programming Language :: Python :: 3
Classifier: License :: OSI Approved :: MIT License
Classifier: Operating System :: OS Independent
Requires-Python: >=3.5
